setup.py
bin/bam2x
bin/bam2x_ls
lib/bam2x/Annotation.py
lib/bam2x/IO.py
lib/bam2x/Struct.py
lib/bam2x/TableIO.py
lib/bam2x/Translator.py
lib/bam2x/__init__.py
lib/bam2x/gmm.py
lib/bam2x/prob.py
lib/bam2x.egg-info/PKG-INFO
lib/bam2x.egg-info/SOURCES.txt
lib/bam2x.egg-info/dependency_links.txt
lib/bam2x.egg-info/requires.txt
lib/bam2x.egg-info/top_level.txt
lib/bam2x/DBI/DB.py
lib/bam2x/DBI/Templates.py
lib/bam2x/DBI/__init__.py
lib/bam2x/MRun/__init__.py
lib/bam2x/MRun/aggregation_plot.py
lib/bam2x/MRun/bam2peak.py
lib/bam2x/MRun/isoforms.py
lib/bam2x/Run/__init__.py
lib/bam2x/Run/aggregation.py
lib/bam2x/Run/aggregation_bed.py
lib/bam2x/Run/bam2dis.py
lib/bam2x/Run/cmpgene.py
lib/bam2x/Run/count_compatible_reads.py
lib/bam2x/Run/end_peak_calling.py
lib/bam2x/Run/get_spliced_reads.py
lib/bam2x/Run/getanno.py
lib/bam2x/Run/getseq.py
lib/bam2x/Run/group_bed.py
lib/bam2x/Run/json_to_html.py
lib/bam2x/Run/load_bed_to_db.py
lib/bam2x/Run/pileup_compatible_reads.py
lib/bam2x/Run/pileup_to_json.py
lib/bam2x/Run/query_RNASeq.py
lib/bam2x/Run/query_RNASeq_bed.py
lib/bam2x/Run/query_RNA_RPKM.py
lib/bam2x/Run/query_bam.py
lib/bam2x/Run/query_bw.py
lib/bam2x/Run/query_db.py
lib/bam2x/Run/query_tabix.py
lib/bam2x/Run/read.py
lib/bam2x/Run/remove_small_introns.py
lib/bam2x/Run/sort.py
lib/bam2x/Run/tabix.py
lib/bam2x/Run/translator.py
lib/bam2x/Run/Plot/__init__.py
lib/bam2x/Run/Plot/bam2fig.py
lib/bam2x/Tools/LZW.py
lib/bam2x/Tools/__init__.py
lib/bam2x/Turing/TuringCodeBook.py
lib/bam2x/Turing/TuringIO.py
lib/bam2x/Turing/TuringUtils.py
lib/bam2x/Turing/__init__.py