Metadata-Version: 1.0
Name: bam2x
Version: 0.2.6
Summary: bionformatics python lib for query bam files, this version set matplotlib as optional.
Home-page: http://github.com/nimezhu/bam2x
Author: Xiaopeng Zhu
Author-email: nimezhu@gmail.com
License: GNU General Public License
Platform: any
